[{"id":110,"name":"Attard","state_code":"01","type":"local council"},{"id":108,"name":"Balzan","state_code":"02","type":"local council"},{"id":107,"name":"Birgu","state_code":"03","type":"local council"},{"id":97,"name":"Birkirkara","state_code":"04","type":"local council"},{"id":88,"name":"Birżebbuġa","state_code":"05","type":"local council"},{"id":138,"name":"Cospicua","state_code":"06","type":"local council"},{"id":117,"name":"Dingli","state_code":"07","type":"local council"},{"id":129,"name":"Fgura","state_code":"08","type":"local council"},{"id":84,"name":"Floriana","state_code":"09","type":"local council"},{"id":134,"name":"Fontana","state_code":"10","type":"local council"},{"id":130,"name":"Għajnsielem","state_code":"13","type":"local council"},{"id":92,"name":"Għarb","state_code":"14","type":"local council"},{"id":120,"name":"Għargħur","state_code":"15","type":"local council"},{"id":106,"name":"Għasri","state_code":"16","type":"local council"},{"id":124,"name":"Għaxaq","state_code":"17","type":"local council"},{"id":118,"name":"Gudja","state_code":"11","type":"local council"},{"id":113,"name":"Gżira","state_code":"12","type":"local council"},{"id":105,"name":"Ħamrun","state_code":"18","type":"local council"},{"id":93,"name":"Iklin","state_code":"19","type":"local council"},{"id":99,"name":"Kalkara","state_code":"21","type":"local council"},{"id":91,"name":"Kerċem","state_code":"22","type":"local council"},{"id":82,"name":"Kirkop","state_code":"23","type":"local council"},{"id":126,"name":"Lija","state_code":"24","type":"local council"},{"id":77,"name":"Luqa","state_code":"25","type":"local council"},{"id":128,"name":"Marsa","state_code":"26","type":"local council"},{"id":137,"name":"Marsaskala","state_code":"27","type":"local council"},{"id":78,"name":"Marsaxlokk","state_code":"28","type":"local council"},{"id":89,"name":"Mdina","state_code":"29","type":"local council"},{"id":102,"name":"Mellieħa","state_code":"30","type":"local council"},{"id":109,"name":"Mġarr","state_code":"31","type":"local council"},{"id":140,"name":"Mosta","state_code":"32","type":"local council"},{"id":74,"name":"Mqabba","state_code":"33","type":"local council"},{"id":96,"name":"Msida","state_code":"34","type":"local council"},{"id":131,"name":"Mtarfa","state_code":"35","type":"local council"},{"id":132,"name":"Munxar","state_code":"36","type":"local council"},{"id":133,"name":"Nadur","state_code":"37","type":"local council"},{"id":112,"name":"Naxxar","state_code":"38","type":"local council"},{"id":115,"name":"Paola","state_code":"39","type":"local council"},{"id":125,"name":"Pembroke","state_code":"40","type":"local council"},{"id":127,"name":"Pietà","state_code":"41","type":"local council"},{"id":79,"name":"Qala","state_code":"42","type":"local council"},{"id":119,"name":"Qormi","state_code":"43","type":"local council"},{"id":111,"name":"Qrendi","state_code":"44","type":"local council"},{"id":83,"name":"Rabat","state_code":"46","type":"local council"},{"id":75,"name":"San Ġwann","state_code":"49","type":"local council"},{"id":87,"name":"San Lawrenz","state_code":"50","type":"local council"},{"id":116,"name":"Sannat","state_code":"52","type":"local council"},{"id":94,"name":"Santa Luċija","state_code":"53","type":"local council"},{"id":90,"name":"Santa Venera","state_code":"54","type":"local council"},{"id":136,"name":"Senglea","state_code":"20","type":"local council"},{"id":98,"name":"Siġġiewi","state_code":"55","type":"local council"},{"id":104,"name":"Sliema","state_code":"56","type":"local council"},{"id":100,"name":"St. Julian's","state_code":"48","type":"local council"},{"id":139,"name":"St. Paul's Bay","state_code":"51","type":"local council"},{"id":86,"name":"Swieqi","state_code":"57","type":"local council"},{"id":122,"name":"Ta' Xbiex","state_code":"58","type":"local council"},{"id":103,"name":"Tarxien","state_code":"59","type":"local council"},{"id":95,"name":"Valletta","state_code":"60","type":"local council"},{"id":101,"name":"Victoria","state_code":"45","type":"local council"},{"id":114,"name":"Xagħra","state_code":"61","type":"local council"},{"id":121,"name":"Xewkija","state_code":"62","type":"local council"},{"id":81,"name":"Xgħajra","state_code":"63","type":"local council"},{"id":123,"name":"Żabbar","state_code":"64","type":"local council"},{"id":85,"name":"Żebbuġ Gozo","state_code":"65","type":"local council"},{"id":80,"name":"Żebbuġ Malta","state_code":"66","type":"local council"},{"id":135,"name":"Żejtun","state_code":"67","type":"local council"},{"id":76,"name":"Żurrieq","state_code":"68","type":"local council"}]