[{"id":4072,"name":"Auckland","state_code":"AUK","type":"region"},{"id":4074,"name":"Bay of Plenty","state_code":"BOP","type":"region"},{"id":4066,"name":"Canterbury","state_code":"CAN","type":"region"},{"id":4067,"name":"Chatham Islands","state_code":"CIT","type":"special island authority"},{"id":4068,"name":"Gisborne","state_code":"GIS","type":"region"},{"id":4075,"name":"Hawke's Bay","state_code":"HKB","type":"region"},{"id":4060,"name":"Manawatu-Wanganui","state_code":"MWT","type":"region"},{"id":4063,"name":"Marlborough","state_code":"MBH","type":"region"},{"id":4070,"name":"Nelson","state_code":"NSN","type":"region"},{"id":4059,"name":"Northland","state_code":"NTL","type":"region"},{"id":4062,"name":"Otago","state_code":"OTA","type":"region"},{"id":4071,"name":"Southland","state_code":"STL","type":"region"},{"id":4069,"name":"Taranaki","state_code":"TKI","type":"region"},{"id":4073,"name":"Tasman","state_code":"TAS","type":"region"},{"id":4061,"name":"Waikato","state_code":"WKO","type":"region"},{"id":4065,"name":"Wellington","state_code":"WGN","type":"region"},{"id":4064,"name":"West Coast","state_code":"WTC","type":"region"}]